claux/__init__.py
claux/__main__.py
claux/cli.py
claux/i18n.py
claux/commands/__init__.py
claux/commands/agents.py
claux/commands/backup.py
claux/commands/config.py
claux/commands/doctor.py
claux/commands/init.py
claux/commands/interactive.py
claux/commands/interactive_builder.py
claux/commands/interactive_install.py
claux/commands/interactive_launcher.py
claux/commands/interactive_menus.py
claux/commands/interactive_ui.py
claux/commands/lang.py
claux/commands/mcp.py
claux/commands/stats.py
claux/commands/status.py
claux/commands/upgrade.py
claux/commands/wizard.py
claux/core/__init__.py
claux/core/config.py
claux/core/config_manager.py
claux/core/context.py
claux/core/detection.py
claux/core/discovery.py
claux/core/exceptions.py
claux/core/mcp.py
claux/core/messaging.py
claux/core/metrics.py
claux/core/profiles.py
claux/core/toon.py
claux/core/updater.py
claux/core/user_config.py
claux/core/utils.py
claux/core/validation.py
claux/locales/en.json
claux/locales/ru.json
claux/ui/__init__.py
claux/ui/industrial_theme.py
claux/ui/menu.py
claux/ui/navigation.py
claux/ui/tables.py
claux/ui/theme.py
claux-0.3.5.dist-info/licenses/LICENSE
claux-0.3.5.dist-info/METADATA
claux-0.3.5.dist-info/WHEEL
claux-0.3.5.dist-info/entry_points.txt
claux-0.3.5.dist-info/top_level.txt
claux-0.3.5.dist-info/RECORD
