Metadata-Version: 2.4
Name: claux
Version: 0.3.5
Summary: Token-efficient AI automation toolkit with TOML inter-agent communication
Author-email: Ilya Kalinin <kalinin.ilya29@gmail.com>
License: MIT
Project-URL: Homepage, https://github.com/Gerrux/claux
Project-URL: Repository, https://github.com/Gerrux/claux
Project-URL: Issues, https://github.com/Gerrux/claux/issues
Keywords: claude,ai,automation,toml,cli,tokens,optimization
Classifier: Development Status :: 3 - Alpha
Classifier: Intended Audience :: Developers
Classifier: Programming Language :: Python :: 3
Classifier: Programming Language :: Python :: 3.8
Classifier: Programming Language :: Python :: 3.9
Classifier: Programming Language :: Python :: 3.10
Classifier: Programming Language :: Python :: 3.11
Classifier: Programming Language :: Python :: 3.12
Requires-Python: >=3.8
License-File: LICENSE
Requires-Dist: typer[all]>=0.9.0
Requires-Dist: rich>=13.0.0
Requires-Dist: inquirerpy>=0.3.4
Requires-Dist: pyyaml>=6.0
Requires-Dist: questionary>=2.0.0
Requires-Dist: toon-format>=0.9.0b1
Provides-Extra: dev
Requires-Dist: pytest>=7.0.0; extra == "dev"
Requires-Dist: black>=23.0.0; extra == "dev"
Requires-Dist: ruff>=0.1.0; extra == "dev"
Dynamic: license-file
